hl7lw/__init__.py
hl7lw/exceptions.py
hl7lw/mllp.py
hl7lw/parser.py
hl7lw/utils.py
hl7lw-0.1.2.dist-info/METADATA
hl7lw-0.1.2.dist-info/WHEEL
hl7lw-0.1.2.dist-info/licenses/LICENSE
hl7lw-0.1.2.dist-info/licenses/NOTICE
hl7lw-0.1.2.dist-info/RECORD
