Metadata-Version: 2.3
Name: hl7lw
Version: 0.1.2
Summary: Super light weight Hl7 2.x parser
Project-URL: Homepage, https://github.com/acv/hl7lw
Author-email: Alexandre Carmel-Veilleux <acv@miniguru.ca>
Classifier: License :: OSI Approved :: Apache Software License
Classifier: Operating System :: OS Independent
Classifier: Programming Language :: Python :: 3
Requires-Python: >=3.8
